[
  {
    "name": "bcookie",
    "value": "\"v=2&1b1d0ef2-8c34-4f24-8481-dcb8862125f8\"",
    "domain": ".linkedin.com",
    "hostOnly": false,
    "path": "/",
    "secure": true,
    "httpOnly": false,
    "sameSite": "no_restriction",
    "session": false,
    "firstPartyDomain": "",
    "partitionKey": null,
    "expirationDate": 1906543240,
    "storeId": null
  },
  {
    "name": "__cf_bm",
    "value": "wD5LX.XOxJVofYVW6G5Fj98uQIN3zbUp7rxW3gfVtYo-1748863096-1.0.1.1-hxgwIkfaAskCmVX10Y8vljNSaKGykZVCEtYG56Agop40YxNiLhP9DEP2RX_pJqenpp5h3Prkf58G8BuLOYmQSxQ_Dxz3Vl001Sw24shLk0A",
    "domain": ".linkedin.com",
    "hostOnly": false,
    "path": "/",
    "secure": true,
    "httpOnly": false,
    "sameSite": "no_restriction",
    "session": false,
    "firstPartyDomain": "",
    "partitionKey": null,
    "expirationDate": 1906543240,
    "storeId": null
  },
  {
    "name": "bscookie",
    "value": "\"v=1&20250602111816d36391ad-d226-4807-8a53-08957b477c88AQHaQVn5ZlTH-8nPbIZ9V8i1C7WZzf6l\"",
    "domain": ".www.linkedin.com",
    "hostOnly": false,
    "path": "/",
    "secure": true,
    "httpOnly": true,
    "sameSite": "no_restriction",
    "session": false,
    "firstPartyDomain": "",
    "partitionKey": null,
    "expirationDate": 1906543240,
    "storeId": null
  },
  {
    "name": "li_rm",
    "value": "AQH_z3lDYcX1BAAAAZcwXRUU8qbcijf7Dur4u29xl3Ku7R4nVaoAnrOFlTYK1iy3CxjPzjeNcNRmdz1y7iXxieuZ2IAFv6OgitankS-Hqy2RkY7UGBemRpM9",
    "domain": ".www.linkedin.com",
    "hostOnly": false,
    "path": "/",
    "secure": true,
    "httpOnly": true,
    "sameSite": "no_restriction",
    "session": false,
    "firstPartyDomain": "",
    "partitionKey": null,
    "expirationDate": 1906543240,
    "storeId": null
  },
  {
    "name": "li_at",
    "value": "AQEDAVth4CEE3bGYAAABlzBegusAAAGXVGsG604AdNlZPLF1Rdl7O2z_ecVqVjes8KKGcAImwO66PB0JoM9Xrw0FoiNt8PQUtTR42nJyS3TsrWNvWLwaz51Xl4Rg9XxRqmgWu2Y1c9q4Rg8W8xZ_A1gf",
    "domain": ".www.linkedin.com",
    "hostOnly": false,
    "path": "/",
    "secure": true,
    "httpOnly": true,
    "sameSite": "no_restriction",
    "session": false,
    "firstPartyDomain": "",
    "partitionKey": null,
    "expirationDate": 1906543240,
    "storeId": null
  },
  {
    "name": "lidc",
    "value": "\"b=VGST09:s=V:r=V:a=V:p=V:g=3217:u=1:x=1:i=1748863190:t=1748948839:v=2:sig=AQGp9HO02IEKDiqTm1_rtYZMX3RB6CMq\"",
    "domain": ".linkedin.com",
    "hostOnly": false,
    "path": "/",
    "secure": true,
    "httpOnly": false,
    "sameSite": "no_restriction",
    "session": false,
    "firstPartyDomain": "",
    "partitionKey": null,
    "expirationDate": 1906543240,
    "storeId": null
  },
  {
    "name": "JSESSIONID",
    "value": "\"ajax:6680085206175728900\"",
    "domain": ".www.linkedin.com",
    "hostOnly": false,
    "path": "/",
    "secure": true,
    "httpOnly": false,
    "sameSite": "no_restriction",
    "session": false,
    "firstPartyDomain": "",
    "partitionKey": null,
    "expirationDate": 1906543240,
    "storeId": null
  }
]